urncjp/__init__.py
urncjp/_version.py
urncjp/handlers.py
urncjp-0.1.14.data/data/etc/jupyter/jupyter_server_config.d/urncjp.json
urncjp-0.1.14.data/data/share/jupyter/labextensions/urncjp/package.json
urncjp-0.1.14.data/data/share/jupyter/labextensions/urncjp/schemas/urncjp/package.json.orig
urncjp-0.1.14.data/data/share/jupyter/labextensions/urncjp/schemas/urncjp/plugin.json
urncjp-0.1.14.data/data/share/jupyter/labextensions/urncjp/static/25.798a43947c018e900607.js
urncjp-0.1.14.data/data/share/jupyter/labextensions/urncjp/static/675.2831667a3955ca019271.js
urncjp-0.1.14.data/data/share/jupyter/labextensions/urncjp/static/851.aa6489e3b989d4c74164.js
urncjp-0.1.14.data/data/share/jupyter/labextensions/urncjp/static/remoteEntry.2866fda094cf26d5dbf0.js
urncjp-0.1.14.data/data/share/jupyter/labextensions/urncjp/static/style.js
urncjp-0.1.14.data/data/share/jupyter/labextensions/urncjp/static/third-party-licenses.json
urncjp-0.1.14.data/data/share/jupyter/labextensions/urncjp/install.json
urncjp-0.1.14.dist-info/METADATA
urncjp-0.1.14.dist-info/WHEEL
urncjp-0.1.14.dist-info/licenses/LICENSE
urncjp-0.1.14.dist-info/RECORD
